tests/__init__.py
tests/conftest.py
tests/test_config.py
tests/test_features.py
tests/test_model.py
tests/test_oracle.py
tests/test_parser.py
tupa/__init__.py
tupa/__main__.py
tupa/__version__.py
tupa/action.py
tupa/config.py
tupa/labels.py
tupa/model.py
tupa/model_util.py
tupa/oracle.py
tupa/parse.py
tupa/traceutil.py
tupa/classifiers/__init__.py
tupa/classifiers/classifier.py
tupa/classifiers/noop.py
tupa/classifiers/linear/__init__.py
tupa/classifiers/linear/sparse_perceptron.py
tupa/classifiers/nn/__init__.py
tupa/classifiers/nn/birnn.py
tupa/classifiers/nn/constants.py
tupa/classifiers/nn/mlp.py
tupa/classifiers/nn/neural_network.py
tupa/classifiers/nn/sub_model.py
tupa/classifiers/nn/util.py
tupa/features/__init__.py
tupa/features/dense_features.py
tupa/features/empty_features.py
tupa/features/feature_extractor.py
tupa/features/feature_params.py
tupa/features/sparse_features.py
tupa/scripts/__init__.py
tupa/scripts/conll18_ud_eval.py
tupa/scripts/dump_vocab.py
tupa/scripts/enum_to_json.py
tupa/scripts/export.py
tupa/scripts/load_save.py
tupa/scripts/strip_multitask.py
tupa/scripts/tune.py
tupa/scripts/visualize_learning_curve.py
tupa/scripts/viz.py
tupa/states/__init__.py
tupa/states/edge.py
tupa/states/node.py
tupa/states/state.py
TUPA-1.4.2.dist-info/LICENSE.txt
TUPA-1.4.2.dist-info/METADATA
TUPA-1.4.2.dist-info/WHEEL
TUPA-1.4.2.dist-info/entry_points.txt
TUPA-1.4.2.dist-info/top_level.txt
TUPA-1.4.2.dist-info/RECORD
