Metadata-Version: 2.1
Name: TUPA
Version: 1.4.2
Summary: Transition-based UCCA Parser
Home-page: https://github.com/huji-nlp/tupa
Author: Daniel Hershcovich
Author-email: danielh@cs.huji.ac.il
License: UNKNOWN
Platform: UNKNOWN
Classifier: Development Status :: 4 - Beta
Classifier: Environment :: Console
Classifier: Intended Audience :: Science/Research
Classifier: License :: OSI Approved :: GNU General Public License v3 or later (GPLv3+)
Classifier: Operating System :: POSIX :: Linux
Classifier: Programming Language :: Python :: 3.6
Classifier: Topic :: Text Processing :: Linguistic
Classifier: Topic :: Scientific/Engineering :: Artificial Intelligence
Requires-Dist: numpy (>=1.15.0)
Requires-Dist: cython (>=0.29)
Requires-Dist: tqdm (>=4.32.2)
Requires-Dist: configargparse (>=0.14.0)
Requires-Dist: ucca (<1.3,>=1.2.3)
Requires-Dist: semstr[amr] (<1.3,>=1.2.2)
Requires-Dist: dynet (==2.1)
Requires-Dist: logbook (>=1.5.2)
Provides-Extra: bert
Requires-Dist: torch (==1.3.1) ; extra == 'bert'
Requires-Dist: pytorch-pretrained-bert (==0.6.2) ; extra == 'bert'
Provides-Extra: server
Requires-Dist: Flask (>=0.12.2) ; extra == 'server'
Requires-Dist: Flask-Assets (>=0.12) ; extra == 'server'
Requires-Dist: Flask-Compress (>=1.4.0) ; extra == 'server'
Requires-Dist: Jinja2 (>=2.9.6) ; extra == 'server'
Requires-Dist: matplotlib (>=2.0.2) ; extra == 'server'
Requires-Dist: networkx (>=1.11) ; extra == 'server'
Requires-Dist: webassets (>=0.12.1) ; extra == 'server'
Provides-Extra: viz
Requires-Dist: scipy ; extra == 'viz'
Requires-Dist: pillow ; extra == 'viz'
Requires-Dist: matplotlib ; extra == 'viz'
